wololo/__init__.py
wololo/adapters.py
wololo/converters.py
wololo/tracers.py
wololo/transformers.py
wololo/algorithms/__init__.py
wololo/algorithms/bbvi.py
wololo/algorithms/sensitivity.py
wololo/algorithms/svgd.py
wololo-0.2.0.dist-info/METADATA
wololo-0.2.0.dist-info/WHEEL
wololo-0.2.0.dist-info/top_level.txt
wololo-0.2.0.dist-info/RECORD
